Metadata-Version: 2.1
Name: square-faaziz
Version: 0.12
Summary: Function
Author: Farid Azizov
Author-email: <farid_azizov@protonmail.com>
Keywords: python,farid azizov
Classifier: Development Status :: 1 - Planning
Classifier: Intended Audience :: Developers
Classifier: Programming Language :: Python :: 3
Classifier: Operating System :: Unix
Classifier: Operating System :: MacOS :: MacOS X
Classifier: Operating System :: Microsoft :: Windows
